bloodyAD/__init__.py
bloodyAD/exceptions.py
bloodyAD/main.py
bloodyAD/md4.py
bloodyAD/patch.py
bloodyAD/utils.py
bloodyAD/asciitree/__init__.py
bloodyAD/asciitree/drawing.py
bloodyAD/asciitree/traversal.py
bloodyAD/asciitree/util.py
bloodyAD/cli_modules/__init__.py
bloodyAD/cli_modules/add.py
bloodyAD/cli_modules/get.py
bloodyAD/cli_modules/msldap.py
bloodyAD/cli_modules/remove.py
bloodyAD/cli_modules/set.py
bloodyAD/formatters/__init__.py
bloodyAD/formatters/accesscontrol.py
bloodyAD/formatters/adschema.py
bloodyAD/formatters/bloodhound.py
bloodyAD/formatters/common.py
bloodyAD/formatters/cryptography.py
bloodyAD/formatters/dns.py
bloodyAD/formatters/formatters.py
bloodyAD/formatters/ldaptypes.py
bloodyAD/formatters/structure.py
bloodyAD/network/config.py
bloodyAD/network/ldap.py
bloodyad-2.5.3.dist-info/METADATA
bloodyad-2.5.3.dist-info/WHEEL
bloodyad-2.5.3.dist-info/entry_points.txt
bloodyad-2.5.3.dist-info/licenses/LICENSE
bloodyad-2.5.3.dist-info/RECORD
