Metadata-Version: 2.4
Name: bloodyAD
Version: 2.5.3
Summary: AD Privesc Swiss Army Knife
Project-URL: Homepage, https://github.com/CravateRouge/bloodyAD
Project-URL: Bug Tracker, https://github.com/CravateRouge/bloodyAD/issues
Author-email: CravateRouge <baptiste@cravaterouge.com>
License-File: LICENSE
Classifier: License :: OSI Approved :: MIT License
Classifier: Operating System :: OS Independent
Classifier: Programming Language :: Python :: 3
Requires-Python: >=3.8
Requires-Dist: asn1crypto==1.5.1
Requires-Dist: badldap>=0.7.4
Requires-Dist: cryptography==44.0.2
Requires-Dist: kerbad>=0.5.9
Requires-Dist: winacl==0.1.9
